tinyagent/__init__.py
tinyagent/py.typed
tinyagent/agents/__init__.py
tinyagent/agents/code.py
tinyagent/agents/react.py
tinyagent/core/__init__.py
tinyagent/core/exceptions.py
tinyagent/core/finalizer.py
tinyagent/core/registry.py
tinyagent/core/types.py
tinyagent/prompts/__init__.py
tinyagent/prompts/loader.py
tinyagent/prompts/templates.py
tinyagent/tools/__init__.py
tinyagent/tools/builtin/__init__.py
tinyagent/tools/builtin/web_search.py
tiny_agent_os-0.73.5.dist-info/METADATA
tiny_agent_os-0.73.5.dist-info/WHEEL
tiny_agent_os-0.73.5.dist-info/top_level.txt
tiny_agent_os-0.73.5.dist-info/RECORD
