Metadata-Version: 2.4
Name: tiny-agent-os
Version: 0.73.5
Summary: A streamlined framework for building powerful LLM-powered agents that actually work
Author: alchemiststudios.ai
License-Expression: BUSL-1.1
Project-URL: Homepage, https://tinyagent.xyz
Project-URL: Repository, https://github.com/alchemiststudiosDOTai/tinyAgent
Project-URL: Issues, https://github.com/alchemiststudiosDOTai/tinyAgent/issues
Keywords: ai,agent,llm,openai,gpt,react
Classifier: Development Status :: 4 - Beta
Classifier: Intended Audience :: Developers
Classifier: Programming Language :: Python :: 3
Classifier: Programming Language :: Python :: 3.10
Classifier: Programming Language :: Python :: 3.11
Classifier: Programming Language :: Python :: 3.12
Classifier: Operating System :: OS Independent
Classifier: Topic :: Scientific/Engineering :: Artificial Intelligence
Requires-Python: >=3.10
Requires-Dist: openai>=1.0
Requires-Dist: pytest>=8.0
Requires-Dist: pre-commit>=4.0
Requires-Dist: python-dotenv>=1.0
